setup.py
lijitao.egg-info/PKG-INFO
lijitao.egg-info/SOURCES.txt
lijitao.egg-info/dependency_links.txt
lijitao.egg-info/top_level.txt
patchfly/__init__.py
patchfly/patchfly.py
patchfly/test.py